eir_auto_gp/__init__.py
eir_auto_gp/multi_task/__init__.py
eir_auto_gp/multi_task/analysis/__init__.py
eir_auto_gp/multi_task/analysis/run_analysis.py
eir_auto_gp/multi_task/modelling/__init__.py
eir_auto_gp/multi_task/modelling/configs.py
eir_auto_gp/multi_task/modelling/run_modelling.py
eir_auto_gp/multi_task/run_multi_task.py
eir_auto_gp/post_analysis/__init__.py
eir_auto_gp/post_analysis/common/__init__.py
eir_auto_gp/post_analysis/common/data_preparation.py
eir_auto_gp/post_analysis/complexity_analysis/__init__.py
eir_auto_gp/post_analysis/complexity_analysis/modelling.py
eir_auto_gp/post_analysis/complexity_analysis/viz.py
eir_auto_gp/post_analysis/effect_analysis/__init__.py
eir_auto_gp/post_analysis/effect_analysis/genotype_effects.py
eir_auto_gp/post_analysis/effect_analysis/gxe_interaction_effects.py
eir_auto_gp/post_analysis/effect_analysis/interaction_effects.py
eir_auto_gp/post_analysis/effect_analysis/viz_genotype_effects.py
eir_auto_gp/post_analysis/effect_analysis/viz_interaction_effects_graph.py
eir_auto_gp/post_analysis/effect_analysis/viz_interaction_effects_point.py
eir_auto_gp/post_analysis/iterative_complexity_analysis.py
eir_auto_gp/post_analysis/run_complexity_analysis.py
eir_auto_gp/post_analysis/run_effect_analysis.py
eir_auto_gp/post_analysis/run_post_analysis.py
eir_auto_gp/predict/__init__.py
eir_auto_gp/predict/data_preparation_utils.py
eir_auto_gp/predict/pack.py
eir_auto_gp/predict/prepare_data.py
eir_auto_gp/predict/run_predict.py
eir_auto_gp/preprocess/__init__.py
eir_auto_gp/preprocess/common.py
eir_auto_gp/preprocess/converge.py
eir_auto_gp/preprocess/genotype.py
eir_auto_gp/preprocess/gwas_pre_selection.py
eir_auto_gp/preprocess/tabular.py
eir_auto_gp/single_task/__init__.py
eir_auto_gp/single_task/analysis/__init__.py
eir_auto_gp/single_task/analysis/run_analysis.py
eir_auto_gp/single_task/modelling/__init__.py
eir_auto_gp/single_task/modelling/configs.py
eir_auto_gp/single_task/modelling/dl_feature_selection.py
eir_auto_gp-0.9.0.dist-info/LICENSE
eir_auto_gp-0.9.0.dist-info/METADATA
eir_auto_gp-0.9.0.dist-info/WHEEL
eir_auto_gp-0.9.0.dist-info/entry_points.txt
eir_auto_gp-0.9.0.dist-info/RECORD
