Metadata-Version: 2.3
Name: EIR-auto-GP
Version: 0.9.0
Summary: 
Author: Arnor Sigurdsson
Author-email: arnor-sigurdsson@users.noreply.github.com
Requires-Python: >=3.12,<3.12.10
Classifier: Programming Language :: Python :: 3
Classifier: Programming Language :: Python :: 3.12
Requires-Dist: aislib (>=0.3.0,<0.4.0)
Requires-Dist: deeplake (==4.2.6)
Requires-Dist: eir-dl (>=0.13.6,<0.14.0)
Requires-Dist: lxml (>=5.2.2,<6.0.0)
Requires-Dist: networkx (>=3.3,<4.0)
Requires-Dist: nxviz (>=0.7.4,<0.8.0)
Requires-Dist: pandas (>=2.2.2,<3.0.0)
Requires-Dist: plink-pipelines (==0.7.0)
Requires-Dist: polars (>=1.15.0,<2.0.0)
Requires-Dist: psutil (>=5.9.8,<6.0.0)
Requires-Dist: qmplot (>=0.3.2,<0.4.0)
Requires-Dist: rich (>=13.7.1,<14.0.0)
Requires-Dist: scikit-optimize (>=0.9.0,<0.10.0)
Requires-Dist: statsmodels (>=0.14.0,<0.15.0)
Requires-Dist: xgboost (>=2.0.3,<3.0.0)
